platon_abi/__init__.py
platon_abi/abi.py
platon_abi/base.py
platon_abi/codec.py
platon_abi/constants.py
platon_abi/decoding.py
platon_abi/encoding.py
platon_abi/exceptions.py
platon_abi/grammar.py
platon_abi/packed.py
platon_abi/py.typed
platon_abi/registry.py
platon_abi/tools/__init__.py
platon_abi/tools/_strategies.py
platon_abi/utils/__init__.py
platon_abi/utils/numeric.py
platon_abi/utils/padding.py
platon_abi/utils/string.py
platon_abi-2.1.3.dist-info/LICENSE
platon_abi-2.1.3.dist-info/METADATA
platon_abi-2.1.3.dist-info/WHEEL
platon_abi-2.1.3.dist-info/top_level.txt
platon_abi-2.1.3.dist-info/RECORD
