Metadata-Version: 2.1
Name: platon-abi
Version: 2.1.3
Summary: platon_abi: Python utilities for working with platon ABI definitions, especially encoding and decoding
Home-page: https://github.com/platonnetwork/platon-abi
Author: Shinnng
Author-email: shinnng@outlook.com
License: MIT
Keywords: platon
Platform: UNKNOWN
Classifier: Development Status :: 5 - Production/Stable
Classifier: Intended Audience :: Developers
Classifier: License :: OSI Approved :: MIT License
Classifier: Natural Language :: English
Classifier: Programming Language :: Python :: 3
Classifier: Programming Language :: Python :: 3.6
Classifier: Programming Language :: Python :: 3.7
Requires-Python: >=3.6, <4
License-File: LICENSE
Requires-Dist: platon-utils (<2.0.0,>=1.2.0)
Requires-Dist: platon-typing (<3.0.0,>=2.0.0)
Requires-Dist: parsimonious (<0.9.0,>=0.8.0)
Provides-Extra: dev
Requires-Dist: bumpversion (<1,>=0.5.3) ; extra == 'dev'
Requires-Dist: pytest-watch (<5,>=4.1.0) ; extra == 'dev'
Requires-Dist: wheel ; extra == 'dev'
Requires-Dist: twine ; extra == 'dev'
Requires-Dist: ipython ; extra == 'dev'
Requires-Dist: pytest (==4.4.1) ; extra == 'dev'
Requires-Dist: pytest-pythonpath (>=0.7.1) ; extra == 'dev'
Requires-Dist: pytest-xdist (==1.22.3) ; extra == 'dev'
Requires-Dist: tox (<3,>=2.9.1) ; extra == 'dev'
Requires-Dist: platon-hash[pycryptodome] ; extra == 'dev'
Requires-Dist: hypothesis (<4,>=3.6.1) ; extra == 'dev'
Requires-Dist: flake8 (==3.4.1) ; extra == 'dev'
Requires-Dist: isort (<5,>=4.2.15) ; extra == 'dev'
Requires-Dist: mypy (==0.701) ; extra == 'dev'
Requires-Dist: pydocstyle (<4,>=3.0.0) ; extra == 'dev'
Requires-Dist: Sphinx (<2,>=1.6.5) ; extra == 'dev'
Requires-Dist: sphinx-rtd-theme (>=0.1.9) ; extra == 'dev'
Requires-Dist: towncrier (<20,>=19.2.0) ; extra == 'dev'
Provides-Extra: doc
Requires-Dist: Sphinx (<2,>=1.6.5) ; extra == 'doc'
Requires-Dist: sphinx-rtd-theme (>=0.1.9) ; extra == 'doc'
Requires-Dist: towncrier (<20,>=19.2.0) ; extra == 'doc'
Provides-Extra: lint
Requires-Dist: flake8 (==3.4.1) ; extra == 'lint'
Requires-Dist: isort (<5,>=4.2.15) ; extra == 'lint'
Requires-Dist: mypy (==0.701) ; extra == 'lint'
Requires-Dist: pydocstyle (<4,>=3.0.0) ; extra == 'lint'
Provides-Extra: test
Requires-Dist: pytest (==4.4.1) ; extra == 'test'
Requires-Dist: pytest-pythonpath (>=0.7.1) ; extra == 'test'
Requires-Dist: pytest-xdist (==1.22.3) ; extra == 'test'
Requires-Dist: tox (<3,>=2.9.1) ; extra == 'test'
Requires-Dist: platon-hash[pycryptodome] ; extra == 'test'
Requires-Dist: hypothesis (<4,>=3.6.1) ; extra == 'test'
Provides-Extra: tools
Requires-Dist: hypothesis (<4,>=3.6.1) ; extra == 'tools'
